pyeds/__init__.py
pyeds/coordinator.py
pyeds/fsm.py
pyeds/lib.py
pyeds-20.9.0.dist-info/LICENSE
pyeds-20.9.0.dist-info/METADATA
pyeds-20.9.0.dist-info/WHEEL
pyeds-20.9.0.dist-info/entry_points.txt
pyeds-20.9.0.dist-info/top_level.txt
pyeds-20.9.0.dist-info/RECORD
