Metadata-Version: 2.1
Name: pyeds
Version: 20.9.0
Summary: Python Event Driven System
Home-page: https://github.com/nradulovic
Author: Nenad Radulovic
Author-email: nenad.b.radulovic@gmail.com
License: LGPL
Keywords: fsm hsm state finite event machine
Platform: UNKNOWN
Classifier: Development Status :: 4 - Beta
Classifier: License :: OSI Approved :: GNU Lesser General Public License v3 (LGPLv3)
Classifier: Programming Language :: Python :: 3.3
Classifier: Programming Language :: Python :: 3.4
Classifier: Programming Language :: Python :: 3.5
Classifier: Programming Language :: Python :: 3.6
Classifier: Operating System :: POSIX :: Linux
Classifier: Topic :: Software Development :: Libraries
